directorium/__init__.py
directorium/api.py
directorium/directorium.py
directorium/event.py
directorium/utils.py
directorium-0.2.0.dist-info/METADATA
directorium-0.2.0.dist-info/WHEEL
directorium-0.2.0.dist-info/licenses/LICENSE
directorium-0.2.0.dist-info/RECORD
