Metadata-Version: 2.3
Name: directorium
Version: 0.2.0
Summary: Wrapper for the public API of https://eucharistiefeier.de/lk/
Project-URL: Repository, https://github.com/MatthiasGi/directorium
Project-URL: Issues, https://github.com/MatthiasGi/directorium/issues
Project-URL: Documentation, https://matthiasgi.github.io/directorium/directorium.html
Author-email: Matthias Gianfelice <matthias@gianfelice.de>
License-File: LICENSE
Keywords: catholic,church,eucharistiefeier,liturgy,mass
Classifier: License :: OSI Approved :: MIT License
Classifier: Operating System :: OS Independent
Classifier: Programming Language :: Python :: 3
Requires-Python: >=3.10
Requires-Dist: platformdirs
Requires-Dist: requests
Requires-Dist: typing-extensions
Provides-Extra: development
Requires-Dist: pdoc; extra == 'development'
Requires-Dist: pre-commit; extra == 'development'
Requires-Dist: twine; extra == 'development'
Provides-Extra: test
Requires-Dist: pytest; extra == 'test'
